{"n_top_pairs":20,"total_pairs":600,"class_names":["void/sky","lane/edge","road","vegetation","vehicle"],"class_colors":[[50,50,60],[100,200,255],[80,80,80],[120,200,80],[255,100,100]],"aggregate":{"mean_wrong_bare":52.515,"mean_wrong_side":52.836666666666666,"total_pixels_per_frame":196608,"pairs_helped":102,"pairs_hurt":150,"pairs_unchanged":348},"pairs":[{"pair":517,"wrong_pixels_bare":131,"wrong_pixels_side":126,"fixed_pixels":14,"hurt_pixels":9,"net_fixed":5,"total_changed":23,"corrections":[{"type":"x2","n":1},{"type":"pose","vals":[5,5,-1]}]},{"pair":585,"wrong_pixels_bare":66,"wrong_pixels_side":64,"fixed_pixels":8,"hurt_pixels":6,"net_fixed":2,"total_changed":14,"corrections":[{"type":"x2","n":1}]},{"pair":496,"wrong_pixels_bare":87,"wrong_pixels_side":87,"fixed_pixels":10,"hurt_pixels":10,"net_fixed":0,"total_changed":20,"corrections":[{"type":"x2","n":1},{"type":"cmaes","n":2},{"type":"pattern","n":2}]},{"pair":511,"wrong_pixels_bare":79,"wrong_pixels_side":79,"fixed_pixels":8,"hurt_pixels":8,"net_fixed":0,"total_changed":16,"corrections":[{"type":"x2","n":1}]},{"pair":105,"wrong_pixels_bare":104,"wrong_pixels_side":105,"fixed_pixels":22,"hurt_pixels":23,"net_fixed":-1,"total_changed":45,"corrections":[{"type":"x2","n":1},{"type":"pattern","n":2}]},{"pair":552,"wrong_pixels_bare":61,"wrong_pixels_side":62,"fixed_pixels":9,"hurt_pixels":10,"net_fixed":-1,"total_changed":19,"corrections":[{"type":"x2","n":1},{"type":"cmaes","n":2},{"type":"pose","vals":[0,0,1]}]},{"pair":155,"wrong_pixels_bare":57,"wrong_pixels_side":59,"fixed_pixels":7,"hurt_pixels":9,"net_fixed":-2,"total_changed":16,"corrections":[{"type":"x2","n":1},{"type":"cmaes","n":2},{"type":"pattern","n":2},{"type":"pose","vals":[5,5,-5]}]},{"pair":72,"wrong_pixels_bare":94,"wrong_pixels_side":97,"fixed_pixels":6,"hurt_pixels":9,"net_fixed":-3,"total_changed":15,"corrections":[{"type":"x2","n":1},{"type":"pose","vals":[0,5,-5]}]},{"pair":537,"wrong_pixels_bare":94,"wrong_pixels_side":97,"fixed_pixels":6,"hurt_pixels":9,"net_fixed":-3,"total_changed":15,"corrections":[{"type":"x2","n":1}]},{"pair":147,"wrong_pixels_bare":56,"wrong_pixels_side":60,"fixed_pixels":6,"hurt_pixels":10,"net_fixed":-4,"total_changed":16,"corrections":[{"type":"x2","n":1},{"type":"pattern","n":2},{"type":"pose","vals":[0,0,-3]}]},{"pair":108,"wrong_pixels_bare":61,"wrong_pixels_side":65,"fixed_pixels":6,"hurt_pixels":10,"net_fixed":-4,"total_changed":16,"corrections":[{"type":"x2","n":1},{"type":"cmaes","n":2},{"type":"pattern","n":2}]},{"pair":136,"wrong_pixels_bare":67,"wrong_pixels_side":71,"fixed_pixels":5,"hurt_pixels":9,"net_fixed":-4,"total_changed":14,"corrections":[{"type":"x2","n":1},{"type":"pattern","n":2},{"type":"pose","vals":[-5,-3,0]},{"type":"warp","qx":0,"qy":-1}]},{"pair":73,"wrong_pixels_bare":67,"wrong_pixels_side":72,"fixed_pixels":5,"hurt_pixels":10,"net_fixed":-5,"total_changed":15,"corrections":[{"type":"x2","n":1},{"type":"pattern","n":2},{"type":"pose","vals":[5,5,-3]}]},{"pair":132,"wrong_pixels_bare":48,"wrong_pixels_side":54,"fixed_pixels":7,"hurt_pixels":13,"net_fixed":-6,"total_changed":20,"corrections":[{"type":"x2","n":1},{"type":"cmaes","n":2},{"type":"pattern","n":2},{"type":"pose","vals":[-1,3,-1]}]},{"pair":158,"wrong_pixels_bare":68,"wrong_pixels_side":75,"fixed_pixels":7,"hurt_pixels":14,"net_fixed":-7,"total_changed":21,"corrections":[{"type":"x2","n":1},{"type":"cmaes","n":2},{"type":"pattern","n":2}]},{"pair":424,"wrong_pixels_bare":47,"wrong_pixels_side":54,"fixed_pixels":5,"hurt_pixels":12,"net_fixed":-7,"total_changed":18,"corrections":[{"type":"x2","n":1},{"type":"warp","qx":4,"qy":-1}]},{"pair":143,"wrong_pixels_bare":62,"wrong_pixels_side":70,"fixed_pixels":5,"hurt_pixels":13,"net_fixed":-8,"total_changed":18,"corrections":[{"type":"x2","n":1},{"type":"cmaes","n":2},{"type":"pattern","n":2},{"type":"pose","vals":[-1,-5,1]}]},{"pair":544,"wrong_pixels_bare":100,"wrong_pixels_side":108,"fixed_pixels":5,"hurt_pixels":13,"net_fixed":-8,"total_changed":18,"corrections":[{"type":"x2","n":1}]},{"pair":82,"wrong_pixels_bare":48,"wrong_pixels_side":57,"fixed_pixels":2,"hurt_pixels":11,"net_fixed":-9,"total_changed":13,"corrections":[{"type":"x2","n":1},{"type":"warp","qx":5,"qy":-4}]},{"pair":514,"wrong_pixels_bare":95,"wrong_pixels_side":105,"fixed_pixels":4,"hurt_pixels":14,"net_fixed":-10,"total_changed":18,"corrections":[{"type":"x2","n":1},{"type":"warp","qx":-1,"qy":6}]}]}